numderivax/__init__.py
numderivax/dlocal.py
numderivax-0.0.1rc44.post1.dist-info/LICENSE
numderivax-0.0.1rc44.post1.dist-info/WHEEL
numderivax-0.0.1rc44.post1.dist-info/METADATA
numderivax-0.0.1rc44.post1.dist-info/RECORD
